{
  "parent": "feywild:lost_tablet",
  "reputation": 5,
  "icon": "endrem:rogue_eye",
  "start": {
    "title": {
      "text": "Rogue Eye"
    },
    "description": {
      "text": "A recap is required...\n\n  $(b;winter)-The eye was embedded with the power of Agility and Stealth and its creator hid it deep in a jungle only to be retrieved by those with great agility. - $()\n\n How original..."
    }
  },
  "tasks": [
    {
      "item": {
        "item": "endrem:rogue_eye"
      },
      "amount": 1,
      "id": "feywild:item"
    }
  ]
}